README.md
setup.cfg
setup.py
PSCAD/__init__.py
PSCAD/pscad.py
PSCAD.egg-info/PKG-INFO
PSCAD.egg-info/SOURCES.txt
PSCAD.egg-info/dependency_links.txt
PSCAD.egg-info/entry_points.txt
PSCAD.egg-info/requires.txt
PSCAD.egg-info/top_level.txt
PSCAD/lib/__init__.py
PSCAD/lib/core/ConfigurationLoader.py
PSCAD/lib/core/PDFWriter.py
PSCAD/lib/core/__init__.py
PSCAD/lib/core/__version__.py
PSCAD/lib/helpers/__init__.py
PSCAD/lib/helpers/colors.py
PSCAD/lib/helpers/directory_helper.py
PSCAD/lib/helpers/file_helper.py
PSCAD/lib/helpers/ip_utils.py
PSCAD/lib/scanner/ScanComparator.py
PSCAD/lib/scanner/Scanner.py
PSCAD/lib/scanner/__init__.py
PSCAD/lib/sniffer/ARPPoisoner.py
PSCAD/lib/sniffer/NetworkProfile.py
PSCAD/lib/sniffer/Sniffer.py
PSCAD/lib/sniffer/__init__.py