Metadata-Version: 2.1
Name: PSCAD
Version: 1.1.1
Summary: A network toolkit that can be used to scan, sniff and discover hosts.
Home-page: https://github.com/cblopez/pscad
Author: cblopez
License: GPLv3
Platform: UNKNOWN
Classifier: Programming Language :: Python :: 3
Classifier: Topic :: Security
Classifier: Topic :: System :: Networking :: Monitoring
Classifier: Operating System :: Unix
Classifier: License :: OSI Approved :: GNU General Public License v3 (GPLv3)
